README.txt
setup.cfg
setup.py
collective/__init__.py
collective/__init__.pyc
collective.relatedSlideshow.egg-info/PKG-INFO
collective.relatedSlideshow.egg-info/SOURCES.txt
collective.relatedSlideshow.egg-info/dependency_links.txt
collective.relatedSlideshow.egg-info/entry_points.txt
collective.relatedSlideshow.egg-info/namespace_packages.txt
collective.relatedSlideshow.egg-info/not-zip-safe
collective.relatedSlideshow.egg-info/paster_plugins.txt
collective.relatedSlideshow.egg-info/requires.txt
collective.relatedSlideshow.egg-info/top_level.txt
collective/relatedSlideshow/__init__.py
collective/relatedSlideshow/configure.zcml
collective/relatedSlideshow/setuphandlers.py
collective/relatedSlideshow/skins.zcml
collective/relatedSlideshow/tests.py
collective/relatedSlideshow/browser/__init__.py
collective/relatedSlideshow/browser/configure.zcml
collective/relatedSlideshow/browser/relatedSlider_view.pt
collective/relatedSlideshow/browser/relatedSlider_view.py
collective/relatedSlideshow/browser/javascripts/slider.js
collective/relatedSlideshow/browser/javascripts/video.js
collective/relatedSlideshow/browser/stylesheets/slider.css
collective/relatedSlideshow/profiles/default/collective.relatedSlideShow_various.txt
collective/relatedSlideshow/profiles/default/cssregistry.xml
collective/relatedSlideshow/profiles/default/jsregistry.xml
collective/relatedSlideshow/profiles/default/metadata.xml
collective/relatedSlideshow/profiles/default/skins.xml
collective/relatedSlideshow/profiles/default/types/Event.xml
collective/relatedSlideshow/profiles/default/types/Folder.xml
collective/relatedSlideshow/profiles/default/types/Person.xml
collective/relatedSlideshow/profiles/default/types/Topic.xml
collective/relatedSlideshow/profiles/default/types/Work.xml
collective/relatedSlideshow/skins/collective_relatedSlideshow_custom_images/loader_animated.gif
collective/relatedSlideshow/skins/collective_relatedSlideshow_custom_images/play-button.png
collective/relatedSlideshow/skins/collective_relatedSlideshow_custom_templates/main_template.pt
docs/HISTORY.txt
docs/INSTALL.txt
docs/LICENSE.GPL
docs/LICENSE.txt