Metadata-Version: 1.0
Name: collective.relatedSlideshow
Version: 2.4
Summary: Slide show with related items
Home-page: https://svn.v2.nl/plone/collective.slideShow/trunk
Author: David Jonas
Author-email: davidjonasdesign@gmail.com
License: GPL
Keywords: plone slideshow related visual
Platform: UNKNOWN
Classifier: Framework :: Plone
Classifier: Programming Language :: Python
